{
  "account": {
    "login": {
      "title": "вход в приложение",
      "fields": {
        "username": {
          "label": "имя пользователя"
        },
        "password": {
          "label": "пароль"
        }
      },
      "buttons": {
        "signIn": "войти"
      },
      "errors": {
        "invalidCredentials": "неправильное имя пользователя либо пароль",
        "serverError": "ошибка сервера при входе в систему",
        "networkError": "ошибка сети при подключении к серверу",
        "unknownError": "неизвестная ошибка при входе в систему",
        "tooManyAttempts": "слишком много попыток входа, попробуйте через 15 минут"
      },
      "registration": {
        "text": "если у вас нет учетной записи ev2,",
        "link": "зарегистрируйтесь"
      }
    },
    "selfRegistration": {
      "title": "регистрация нового пользователя",
      "titleDisabled": "регистрация новых пользователей отключена",
      "loading": "загрузка настроек регистрации...",
      "fields": {
        "username": {
          "label": "имя пользователя*"
        },
        "password": {
          "label": "пароль*"
        },
        "passwordConfirm": {
          "label": "подтверждение пароля*"
        },
        "surname": {
          "label": "фамилия*"
        },
        "name": {
          "label": "имя*"
        },
        "email": {
          "label": "электронная почта*"
        },
        "phone": {
          "label": "телефон",
          "placeholder": "+7 (###) ###-####"
        }
      },
      "validation": {
        "password": {
          "required": "пароль обязателен",
          "policiesNotLoaded": "настройки политики паролей не загружены - регистрация заблокирована",
          "minLength": "пароль должен содержать минимум {length} символов",
          "maxLength": "пароль не должен превышать {length} символов",
          "lowercase": "пароль должен содержать строчные буквы",
          "uppercase": "пароль должен содержать заглавные буквы",
          "numbers": "пароль должен содержать цифры",
          "specialChars": "пароль должен содержать специальные символы",
          "invalidChars": "пароль содержит недопустимые символы"
        },
        "passwordConfirm": {
          "required": "подтверждение пароля обязательно",
          "mismatch": "пароли не совпадают"
        },
        "username": {
          "required": "имя пользователя обязательно",
          "rulesNotLoaded": "правила валидации не загружены - валидация имени пользователя отключена",
          "minLength": "имя пользователя должно содержать минимум {length} символов",
          "maxLength": "имя пользователя не должно превышать {length} символов",
          "latinOnly": "имя пользователя должно содержать только латинские буквы, цифры, точки, подчеркивания и дефисы",
          "noNumbers": "имя пользователя не должно содержать цифры",
          "noSpecialChars": "имя пользователя не должно содержать специальные символы"
        },
        "email": {
          "required": "электронная почта обязательна",
          "rulesNotLoaded": "правила валидации не загружены - валидация email отключена",
          "format": "неверный формат электронной почты"
        },
        "phone": {
          "format": "неверный формат номера телефона",
          "rulesNotLoaded": "правила валидации не загружены - валидация телефона отключена",
          "invalidRegex": "неверный regex для телефона в системных настройках"
        }
      },
      "buttons": {
        "register": "регистрация"
      },
      "errors": {
        "validation": "ошибка валидации: невалидные поля -",
        "duplicateUsername": "ошибка: такое имя пользователя уже зарегистрировано",
        "duplicateEmail": "ошибка: такой адрес электронной почты уже используется",
        "duplicatePhone": "ошибка: такой номер телефона уже используется",
        "passwordPoliciesLoadFailed": "ошибка загрузки настроек политики паролей",
        "passwordPoliciesNotReady": "настройки политики паролей не готовы - регистрация заблокирована",
        "formValidation": "проверьте правильность заполнения полей формы",
        "serverError": "ошибка сервера при регистрации",
        "networkError": "ошибка сети при отправке данных регистрации"
      },
      "success": {
        "registered": "регистрация успешно завершена",
        "dataSent": "данные регистрационной формы успешно отправлены на сервер"
      },
      "login": {
        "alreadyHaveAccount": "уже есть учетная запись?",
        "signIn": "войдите в систему"
      }
    },
    "sessionData": {
      "title": "технические данные сессии",
      "username": "имя пользователя",
      "jwt": "jwt токен",
      "isLoggedIn": "авторизован",
      "userID": "идентификатор пользователя",
      "issuedAt": "токен выдан",
      "issuer": "издатель токена",
      "expiresAt": "токен истекает",
      "timeUntilExpiry": "сессия истекает через",
      "seconds": "секунд",
      "yes": "да",
      "no": "нет"
    },
    "profile": {
      "title": "профиль пользователя",
      "sections": {
        "personalInfo": "личная информация",
        "contactInfo": "контактные данные",
        "workInfo": "рабочая информация"
      },
      "fields": {
        "lastName": {
          "label": "фамилия",
          "validation": {
            "required": "фамилия обязательна",
            "minLength": "фамилия должна содержать минимум 2 символа",
            "maxLength": "фамилия не должна превышать 50 символов"
          }
        },
        "firstName": {
          "label": "имя",
          "validation": {
            "required": "имя обязательно",
            "minLength": "имя должно содержать минимум 2 символа",
            "maxLength": "имя не должно превышать 50 символов"
          }
        },
        "middleName": {
          "label": "отчество",
          "validation": {
            "maxLength": "отчество не должно превышать 50 символов"
          }
        },
        "gender": {
          "label": "пол",
          "validation": {
            "maxLength": "пол не должен превышать 20 символов"
          },
          "options": {
            "male": "мужской",
            "female": "женский",
            "notDefined": "не указан",
            "notSelected": "не выбрано"
          }
        },
        "phoneNumber": {
          "label": "номер телефона",
          "validation": {
            "format": "неверный формат номера телефона",
            "maxLength": "номер телефона не должен превышать 20 символов"
          }
        },
        "email": {
          "label": "e-mail",
          "validation": {
            "format": "неверный формат email",
            "maxLength": "email не должен превышать 100 символов"
          }
        }
      },
      "actions": {
        "title": "действия",
        "save": "сохранить",
        "update": "обновить",
        "changePassword": "изменить пароль"
      },
      "messages": {
        "saveSuccess": "данные профиля успешно обновлены",
        "saveError": "ошибка при обновлении данных профиля",
        "loadError": "ошибка загрузки данных профиля",
        "validationError": "пожалуйста, заполните все обязательные поля"
      }
    }
  }
}
